LICENSE
README.rst
django_express-0.4.0.dist-info/DESCRIPTION.rst
django_express-0.4.0.dist-info/METADATA
django_express-0.4.0.dist-info/RECORD
django_express-0.4.0.dist-info/WHEEL
django_express-0.4.0.dist-info/metadata.json
django_express-0.4.0.dist-info/top_level.txt
express/__init__.py
express/apps.py
express/decorators.py
express/http.py
express/tests.py
express/db/__init__.py
express/db/backends/__init__.py
express/db/backends/mongodb/__init__.py
express/db/backends/mongodb/base.py
testa/services/__init__.py
testa/services/api.py
