Metadata-Version: 2.0
Name: django-express
Version: 0.4.0
Summary: Easy Restful APIs with the Django web framework.
Home-page: https://github.com/bluekvirus/django-express
Author: Tim Lauv
Author-email: bluekvirus@gmail.com
License: MIT
Keywords: django,restful api,express,services
Platform: UNKNOWN
Classifier: Development Status :: 4 - Beta
Classifier: Environment :: Web Environment
Classifier: Framework :: Django
Classifier: Operating System :: OS Independent
Classifier: Intended Audience :: Developers
Classifier: Topic :: Software Development :: Build Tools
Classifier: License :: OSI Approved :: MIT License
Classifier: Programming Language :: Python :: 3.5
Classifier: Programming Language :: Python :: 3.6
Provides-Extra: pymongo
Requires-Dist: Django (>=1.11)
Provides-Extra: pymongo
Requires-Dist: pymongo (>=3.4); extra == 'pymongo'
